kcpwd/__init__.py
kcpwd/cli.py
kcpwd/core.py
kcpwd/decorators.py
kcpwd/envexport.py
kcpwd/file_backend.py
kcpwd/helm.py
kcpwd/k8s.py
kcpwd/master_protection.py
kcpwd/platform_utils.py
kcpwd/strength.py
kcpwd/ui/__init__.py
kcpwd/ui/api.py
kcpwd/ui/config.py
kcpwd/ui/sharing.py
kcpwd/ui/static/app.js
kcpwd/ui/static/index.html
kcpwd/ui/static/kcpwd_logo.png
kcpwd/ui/static/styles.css
kcpwd-0.8.1.dist-info/licenses/LICENSE
test/__init__.py
test/test_cli.py
test/test_helm.py
test/test_k8s.py
test/test_master.py
test/test_strength.py
kcpwd-0.8.1.dist-info/METADATA
kcpwd-0.8.1.dist-info/WHEEL
kcpwd-0.8.1.dist-info/entry_points.txt
kcpwd-0.8.1.dist-info/top_level.txt
kcpwd-0.8.1.dist-info/RECORD
