Metadata-Version: 2.4
Name: kcpwd
Version: 0.8.1
Summary: Cross-platform Password Manager with Web UI & Kubernetes Integration - Works everywhere! macOS Keychain, Linux Secret Service, Windows Credential Locker, or encrypted file storage. Native K8s secret sync, Helm integration, zero dependencies required.
Home-page: https://github.com/osmanuygar/kcpwd
Author: osmanuygar
Author-email: osmanuygar@gmail.com
Keywords: password manager cli keychain macos linux windows security decorator library import export backup master-password encryption cross-platform web-ui fastapi credential-locker kubernetes k8s helm secret-management devops gitops argocd flux cicd
Classifier: Development Status :: 4 - Beta
Classifier: Intended Audience :: Developers
Classifier: Intended Audience :: End Users/Desktop
Classifier: Intended Audience :: System Administrators
Classifier: Topic :: Security
Classifier: Topic :: Security :: Cryptography
Classifier: Topic :: Utilities
Classifier: Topic :: Software Development :: Libraries :: Python Modules
Classifier: Topic :: System :: Systems Administration
Classifier: License :: OSI Approved :: MIT License
Classifier: Programming Language :: Python :: 3
Classifier: Programming Language :: Python :: 3.8
Classifier: Programming Language :: Python :: 3.9
Classifier: Programming Language :: Python :: 3.10
Classifier: Programming Language :: Python :: 3.11
Classifier: Programming Language :: Python :: 3.12
Classifier: Operating System :: MacOS
Classifier: Operating System :: POSIX :: Linux
Classifier: Operating System :: Microsoft :: Windows
Classifier: Operating System :: Microsoft :: Windows :: Windows 10
Classifier: Operating System :: Microsoft :: Windows :: Windows 11
Classifier: Environment :: Console
Classifier: Environment :: Web Environment
Requires-Python: >=3.8
License-File: LICENSE
Requires-Dist: click>=8.0.0
Requires-Dist: keyring>=23.0.0
Requires-Dist: cryptography>=41.0.0
Requires-Dist: secretstorage>=3.3.0; sys_platform == "linux"
Requires-Dist: pywin32>=305; sys_platform == "win32"
Requires-Dist: pyyaml>=6.0.0
Provides-Extra: dev
Requires-Dist: pytest>=7.0.0; extra == "dev"
Requires-Dist: pytest-cov>=4.0.0; extra == "dev"
Requires-Dist: build>=0.10.0; extra == "dev"
Requires-Dist: twine>=4.0.0; extra == "dev"
Requires-Dist: cryptography>=41.0.0; extra == "dev"
Requires-Dist: black>=23.0.0; extra == "dev"
Requires-Dist: ruff>=0.1.0; extra == "dev"
Requires-Dist: mypy>=1.7.0; extra == "dev"
Requires-Dist: httpx>=0.25.0; extra == "dev"
Provides-Extra: ui
Requires-Dist: fastapi>=0.104.0; extra == "ui"
Requires-Dist: uvicorn[standard]>=0.24.0; extra == "ui"
Requires-Dist: pydantic>=2.0.0; extra == "ui"
Requires-Dist: python-multipart>=0.0.6; extra == "ui"
Dynamic: author
Dynamic: author-email
Dynamic: classifier
Dynamic: description
Dynamic: description-content-type
Dynamic: home-page
Dynamic: keywords
Dynamic: license-file
Dynamic: provides-extra
Dynamic: requires-dist
Dynamic: requires-python
Dynamic: summary
